pytest_gitconfig-0.9.0.dist-info/METADATA
pytest_gitconfig-0.9.0.dist-info/WHEEL
pytest_gitconfig-0.9.0.dist-info/entry_points.txt
pytest_gitconfig-0.9.0.dist-info/licenses/LICENSE
pytest_gitconfig/VERSION
pytest_gitconfig/__init__.py
pytest_gitconfig/plugin.py
pytest_gitconfig/py.typed
pytest_gitconfig-0.9.0.dist-info/RECORD
