Metadata-Version: 2.4
Name: pytest-gitconfig
Version: 0.9.0
Summary: Provide a Git config sandbox for testing
Author-Email: Axel Haustant <noirbizarre@gmail.com>
License-Expression: MIT
License-File: LICENSE
Classifier: Development Status :: 4 - Beta
Classifier: Intended Audience :: Developers
Classifier: Programming Language :: Python
Classifier: Programming Language :: Python :: 3
Classifier: Programming Language :: Python :: 3 :: Only
Classifier: Programming Language :: Python :: 3.10
Classifier: Programming Language :: Python :: 3.11
Classifier: Programming Language :: Python :: 3.12
Classifier: Programming Language :: Python :: 3.13
Classifier: Programming Language :: Python :: 3.14
Classifier: Typing :: Typed
Project-URL: Homepage, https://github.com/noirbizarre/pytest-gitconfig
Project-URL: Documentation, https://github.com/noirbizarre/pytest-gitconfig#readme
Project-URL: Repository, https://github.com/noirbizarre/pytest-gitconfig
Project-URL: Issues, https://github.com/noirbizarre/pytest-gitconfig/issues
Requires-Python: >=3.10
Requires-Dist: pytest>=7.1.2
